SuSMoST-1.2.19.data/scripts/make-ac-samples
SuSMoST-1.2.19.data/scripts/adlenum
susmost/transferm.cpython-36m-x86_64-linux-gnu.so
susmost/acutils.cpython-36m-x86_64-linux-gnu.so
susmost/supercelllattice.cpython-36m-x86_64-linux-gnu.so
susmost/tds_runge_kutta.py
susmost/rndsvdop.cpython-36m-x86_64-linux-gnu.so
susmost/InteractionField.cpython-36m-x86_64-linux-gnu.so
susmost/InteractionMatrix.cpython-36m-x86_64-linux-gnu.so
susmost/tensors.cpython-36m-x86_64-linux-gnu.so
susmost/latconf.cpython-36m-x86_64-linux-gnu.so
susmost/trg.cpython-36m-x86_64-linux-gnu.so
susmost/make_regr.cpython-36m-x86_64-linux-gnu.so
susmost/lattice.py
susmost/regraph.cpython-36m-x86_64-linux-gnu.so
susmost/latticetask.py
susmost/symmetry.cpython-36m-x86_64-linux-gnu.so
susmost/cli.py
susmost/cell.cpython-36m-x86_64-linux-gnu.so
susmost/sitestate.py
susmost/make_interaction.py
susmost/trgtncpu.cpython-36m-x86_64-linux-gnu.so
susmost/savexyz.py
susmost/trgtncuda.cpython-36m-x86_64-linux-gnu.so
susmost/make_struct.py
susmost/enumphases.cpython-36m-x86_64-linux-gnu.so
susmost/IndexedOrderedDict.cpython-36m-x86_64-linux-gnu.so
susmost/__init__.py
susmost/rndsvdcuda.cpython-36m-x86_64-linux-gnu.so
susmost/cartcoords.cpython-36m-x86_64-linux-gnu.so
susmost/zmatrix.cpython-36m-x86_64-linux-gnu.so
susmost/pbc.cpython-36m-x86_64-linux-gnu.so
susmost/meanfield.cpython-36m-x86_64-linux-gnu.so
susmost/edge.cpython-36m-x86_64-linux-gnu.so
SuSMoST-1.2.19.dist-info/WHEEL
SuSMoST-1.2.19.dist-info/entry_points.txt
SuSMoST-1.2.19.dist-info/top_level.txt
SuSMoST-1.2.19.dist-info/RECORD
SuSMoST-1.2.19.dist-info/METADATA
