Metadata-Version: 2.1
Name: SuSMoST
Version: 1.2.19
Summary: SUrface Science MOdeling and Simulation Toolkit
Home-page: https://susmost.com
License: UNKNOWN
Platform: UNKNOWN
Requires-Dist: numpy (>=1.13.0)
Requires-Dist: setuptools-scm
Requires-Dist: scipy (>=1.3.3)
Requires-Dist: sortedcontainers (>=2.1.0)
Requires-Dist: ase (>=3.18.1)
Requires-Dist: spglib (>=1.11.2)
Requires-Dist: Diophantine (==0.2.0)
Requires-Dist: GitPython
Requires-Dist: mpmath
Requires-Dist: psutil
